{
    "IACHIALE01":[
        "Iachine,\u00a0Alexei",
        "11/5/1973"
    ],
    "IAKOVROM01":[
        "Iakovlev,\u00a0Roman",
        "8/13/1976"
    ],
    "IATSEIOU01":[
        "Iatsev,\u00a0Iouri",
        "3/2/1979"
    ],
    "IBARJOS01":[
        "Ibar,\u00a0Jose",
        "5/4/1969"
    ],
    "IBARRMAN01":[
        "Ibarra,\u00a0Manuel",
        "11/18/1977"
    ],
    "IBBETBRU01":[
        "Ibbetson,\u00a0Bruce",
        "1/13/1953"
    ],
    "IBBOTDER01":[
        "Ibbotson,\u00a0Derek",
        "6/17/1932"
    ],
    "IBRAGANV01":[
        "Ibragimov,\u00a0Anvar",
        "11/27/1965"
    ],
    "IBRAGAYD01":[
        "Ibragimov,\u00a0Aydyn",
        "9/17/1938"
    ],
    "IBRAGMAG01":[
        "Ibragimov,\u00a0Magomed",
        "8/18/1983"
    ],
    "IBRAGMOG01":[
        "Ibragimov,\u00a0Mogamed",
        "7/22/1974"
    ],
    "IBRAHKAR01":[
        "Ibrahim,\u00a0Karam",
        "9/1/1979"
    ],
    "IBRAHMUH01":[
        "Ibrahim,\u00a0Muhammad Qamar",
        "1/14/1968"
    ],
    "IBYFRI01":[
        "Iby,\u00a0Friedl",
        "4/6/1905"
    ],
    "IBZAGSUL01":[
        "Ibzagimov,\u00a0Sultanahmed",
        "3/8/1975"
    ],
    "IBZAIERM01":[
        "Ibzaimov,\u00a0Ermakhan",
        "1/1/1972"
    ],
    "ICHIGMAS01":[
        "Ichiguchi,\u00a0Masamitsu",
        "1/12/1940"
    ],
    "ICHINSHI01":[
        "Ichinoseki,\u00a0Shiro",
        "1/24/1944"
    ],
    "ICHOCHI01":[
        "Icho,\u00a0Chiharu",
        "10/6/1981"
    ],
    "ICHOKAO01":[
        "Icho,\u00a0Kaori",
        "6/13/1984"
    ],
    "IDEHEFAI01":[
        "Idehen,\u00a0Faith",
        "2/5/1973"
    ],
    "IDEMGJOS01":[
        "Idem Guerrini,\u00a0Josefa",
        "9/23/1964"
    ],
    "IDEMJOS01":[
        "Idem,\u00a0Josefa",
        "9/23/1964"
    ],
    "IGALIDAN01":[
        "Igali,\u00a0Daniel",
        "2/3/1974"
    ],
    "IGALYDIA01":[
        "Igaly,\u00a0Diana",
        "1/31/1965"
    ],
    "IGARAHIS01":[
        "Igarashi,\u00a0Hisato",
        "2/19/1951"
    ],
    "IGAYACHI01":[
        "Igaya,\u00a0Chiharu",
        "5/20/1931"
    ],
    "IGBINRIC01":[
        "Igbineghu,\u00a0Richard",
        "4/21/1968"
    ],
    "IGINLJAR01":[
        "Iginla,\u00a0Jarome",
        "7/1/1977"
    ],
    "IGLESRAF01":[
        "Iglesias,\u00a0Rafael",
        "5/25/1924"
    ],
    "IGNATARD01":[
        "Ignatyev,\u00a0Ardalion",
        "11/24/1930"
    ],
    "IGNATDOI01":[
        "Ignat,\u00a0Doina",
        "12/20/1968"
    ],
    "IGNATMIK01":[
        "Ignatyev,\u00a0Mikhail",
        "5/7/1985"
    ],
    "IGOROAND01":[
        "Igorov,\u00a0Andrei",
        "12/10/1939"
    ],
    "IGUCHTAD01":[
        "Iguchi,\u00a0Tadahito",
        "12/14/1974"
    ],
    "IH%C1SZK%C1L01":[
        "Ih\u00e1sz,\u00a0K\u00e1lm\u00e1n",
        "3/6/1941"
    ],
    "IHALAMAR01":[
        "Ihalainen,\u00a0Marianne",
        "2/22/1967"
    ],
    "IHBEERN01":[
        "Ihbe,\u00a0Ernst",
        "12/20/1913"
    ],
    "IHLEAND01":[
        "Ihle,\u00a0Andreas",
        "6/2/1979"
    ],
    "IIDATAK01":[
        "Iida,\u00a0Takako",
        "2/3/1946"
    ],
    "IKEDAKEI01":[
        "Ikeda-Tanaka,\u00a0Keiko",
        "11/11/1933"
    ],
    "IKEDAMIT01":[
        "Ikeda,\u00a0Mitsuo",
        "3/14/1935"
    ],
    "IKEDANAO01":[
        "Ikeda,\u00a0Naohiro",
        "1/17/1940"
    ],
    "IKELAPIE01":[
        "Ikelaar,\u00a0Piet",
        "1/3/1896"
    ],
    "IKETAYUK01":[
        "Iketani,\u00a0Yukio",
        "9/26/1970"
    ],
    "IKHOUISA01":[
        "Ikhouria,\u00a0Isaac",
        "10/9/1947"
    ],
    "IKODIDAN01":[
        "Ikodinovic,\u00a0Danilo",
        "10/4/1976"
    ],
    "IKOLAHEI01":[
        "Ikola,\u00a0Heikki",
        "9/9/1947"
    ],
    "IKOLAWIL01":[
        "Ikola,\u00a0Willard",
        "7/28/1932"
    ],
    "IKONEJOH01":[
        "Ikonen,\u00a0Johanna",
        "1/9/1969"
    ],
    "IKONEV%C4I01":[
        "Ikonen,\u00a0V\u00e4in\u00f6",
        "10/5/1895"
    ],
    "IKPEBVIC01":[
        "Ikpeba,\u00a0Victor",
        "6/12/1973"
    ],
    "ILCHEIRI01":[
        "Ilchenko-Smirnova,\u00a0Irina",
        "8/3/1968"
    ],
    "ILEGEROG01":[
        "Ilegems,\u00a0Roger",
        "12/13/1962"
    ],
    "ILESKAT01":[
        "Iles,\u00a0Katica",
        "3/30/1946"
    ],
    "ILIADILI01":[
        "Iliadis,\u00a0Ilias",
        "11/10/1986"
    ],
    "ILIEVKHR01":[
        "Iliev,\u00a0Khristo",
        "11/7/1951"
    ],
    "ILIEVVAL01":[
        "Ilieva-Kharalampieva,\u00a0Valentina",
        "3/12/1962"
    ],
    "ILIEVZHA01":[
        "Ilieva,\u00a0Zhaneta",
        "10/3/1984"
    ],
    "ILINAVER01":[
        "Ilina,\u00a0Vera",
        "2/20/1974"
    ],
    "ILIUTANA01":[
        "Iliuta,\u00a0Ana",
        "1/10/1958"
    ],
    "ILKOVNIK01":[
        "Ilkov,\u00a0Nikolay",
        "2/21/1955"
    ],
    "ILMANGAR01":[
        "Ilman,\u00a0Gary",
        "8/13/1943"
    ],
    "ILMONTAU01":[
        "Ilmoniemi,\u00a0Tauno",
        "5/16/1893"
    ],
    "ILYENIRI01":[
        "Ilyenkova,\u00a0Irina",
        "4/10/1980"
    ],
    "ILYICLEO01":[
        "Ilyichov,\u00a0Leonid",
        "1/30/1948"
    ],
    "ILYINANA01":[
        "Ilyin,\u00a0Anatoly",
        "6/27/1931"
    ],
    "ILYINNAD01":[
        "Ilyina,\u00a0Nadezhda",
        "1/14/1949"
    ],
    "ILYINVAL01":[
        "Ilyinykh,\u00a0Valery",
        "8/7/1947"
    ],
    "ILYINVAS01":[
        "Ilyin,\u00a0Vasily",
        "1/8/1949"
    ],
    "IMAOKMAK01":[
        "Imaoka,\u00a0Makoto",
        "9/11/1974"
    ],
    "IMDON01":[
        "Im ,\u00a0Dong-Hyun",
        "5/12/1986"
    ],
    "IMHOFDAR01":[
        "Imhoff,\u00a0Darrall",
        "10/11/1938"
    ],
    "IMISORAC01":[
        "Imison,\u00a0Rachel",
        "12/16/1978"
    ],
    "IMMELJAN01":[
        "Immel,\u00a0Jan Olaf",
        "3/14/1976"
    ],
    "IMMERDAN01":[
        "Immerfall,\u00a0Daniel",
        "12/14/1955"
    ],
    "IMMESPET01":[
        "Immesberger,\u00a0Peter",
        "4/18/1960"
    ],
    "IMOHCHI01":[
        "Imoh,\u00a0Chidi",
        "8/27/1963"
    ],
    "IMREG%C9Z01":[
        "Imre,\u00a0G\u00e9za",
        "12/23/1974"
    ],
    "INDRISRI01":[
        "Indriyani,\u00a0Sri",
        "11/12/1978"
    ],
    "INDURMIG01":[
        "Indurain,\u00a0Miguel",
        "7/16/1964"
    ],
    "INESOTON01":[
        "Ineson,\u00a0Tony",
        "4/23/1950"
    ],
    "INESSSIM01":[
        "Iness,\u00a0Sim",
        "7/9/1930"
    ],
    "INGEBEUG01":[
        "Ingebretsen,\u00a0Eugen",
        "12/30/1884"
    ],
    "INGEBOLA01":[
        "Ingebretsen,\u00a0Olaf",
        "5/24/1892"
    ],
    "INGRASHE01":[
        "Ingram,\u00a0Sheila",
        "3/23/1957"
    ],
    "INNAUTON01":[
        "Innauer,\u00a0Toni",
        "4/1/1958"
    ],
    "INNOCAZE01":[
        "Innocenti,\u00a0Azeglio",
        "n/a"
    ],
    "INNOCFIL01":[
        "Innocenti,\u00a0Filiberto",
        "n/a"
    ],
    "INOHAJUN01":[
        "Inohara,\u00a0Junzo",
        "n/a"
    ],
    "INOKUISA01":[
        "Inokuma,\u00a0Isao",
        "2/4/1938"
    ],
    "INOUEJUN01":[
        "Inoue,\u00a0Junichi",
        "12/26/1971"
    ],
    "INOUEKEN01":[
        "Inoue,\u00a0Kenji",
        "11/5/1976"
    ],
    "INOUEKOS01":[
        "Inoue,\u00a0Kosei",
        "5/15/1978"
    ],
    "INOUEMAS01":[
        "Inoue,\u00a0Masaki",
        "7/25/1979"
    ],
    "INOUESET01":[
        "Inoue,\u00a0Setsuko",
        "9/16/1946"
    ],
    "INUIEMI01":[
        "Inui,\u00a0Emi",
        "10/26/1983"
    ],
    "INVERGIO01":[
        "Invernizzi,\u00a0Giovanni",
        "6/17/1926"
    ],
    "INZHUGAL01":[
        "Inzhuvatova,\u00a0Galina",
        "2/28/1952"
    ],
    "IOJAVIO01":[
        "Ioja,\u00a0Viorica",
        "2/26/1962"
    ],
    "IONCOR01":[
        "Ion,\u00a0Corneliu",
        "6/27/1951"
    ],
    "IONESATA01":[
        "Ionescu,\u00a0Atanasia",
        "3/19/1935"
    ],
    "IONESCLA01":[
        "Ionescu,\u00a0Claudiu Eugen",
        "8/24/1959"
    ],
    "IONESNAS01":[
        "Ionescu,\u00a0Nastasia",
        "3/5/1954"
    ],
    "IONESVAL01":[
        "Ionescu,\u00a0Valeria",
        "8/2/1960"
    ],
    "IONITRAL01":[
        "Ionita,\u00a0Raluca Andreea",
        "6/9/1976"
    ],
    "IONOVANA01":[
        "Ionov,\u00a0Anatoly",
        "5/23/1939"
    ],
    "IONOVVYA01":[
        "Ionov,\u00a0Vyacheslav",
        "6/26/1940"
    ],
    "IORGAVAS01":[
        "Iorga,\u00a0Vasile",
        "2/19/1945"
    ],
    "IOSUBPET01":[
        "Iosub,\u00a0Petru",
        "6/16/1961"
    ],
    "IOUCHANG01":[
        "Iouchkova,\u00a0Angelina",
        "n/a"
    ],
    "IOVANSON01":[
        "Iovan,\u00a0Sonia",
        "9/29/1935"
    ],
    "IOVTCIOR01":[
        "Iovtchev,\u00a0Iordan",
        "2/24/1973"
    ],
    "IQBALZAF01":[
        "Iqbal,\u00a0Zafar",
        "6/20/1956"
    ],
    "IRELAALE01":[
        "Ireland,\u00a0Alexander",
        "2/11/1901"
    ],
    "IRETOALB01":[
        "Ireton,\u00a0Albert",
        "5/15/1879"
    ],
    "IRIETAK01":[
        "Irie,\u00a0Takashi",
        "5/10/1958"
    ],
    "IRIETOS01":[
        "Irie,\u00a0Toshio",
        "11/5/1911"
    ],
    "IRIMIDAN01":[
        "Irimiciuc,\u00a0Dan",
        "5/9/1949"
    ],
    "IRMERKAR01":[
        "Irmer,\u00a0Karl-Heinz",
        "7/22/1903"
    ],
    "IRMSCHAR01":[
        "Irmscher,\u00a0Harald",
        "2/12/1946"
    ],
    "IRONSFRA01":[
        "Irons,\u00a0Frank",
        "3/23/1886"
    ],
    "IRVINJAM01":[
        "Irvine,\u00a0James",
        "12/2/1948"
    ],
    "IRVINSTU01":[
        "Irving,\u00a0Stuart",
        "2/2/1949"
    ],
    "IRWINJUN01":[
        "Irwin,\u00a0Juno",
        "11/22/1928"
    ],
    "ISAACHAR01":[
        "Isaacs,\u00a0Harry",
        "1/26/1908"
    ],
    "ISAACREY01":[
        "Isaac,\u00a0Rey",
        "1/3/1973"
    ],
    "ISAACWAL01":[
        "Isaacs,\u00a0Walter",
        "n/a"
    ],
    "ISACHBOR01":[
        "Isachenko,\u00a0Boris",
        "12/26/1958"
    ],
    "ISAEVKHA01":[
        "Isaev,\u00a0Khasan",
        "11/9/1952"
    ],
    "ISAKOMIL01":[
        "Isakovic,\u00a0Mile",
        "1/17/1958"
    ],
    "ISAKONAT01":[
        "Isakova,\u00a0Natalya",
        "10/23/1966"
    ],
    "ISAKOVLA01":[
        "Isakov,\u00a0Vladimir",
        "2/28/1970"
    ],
    "ISAKSMAG01":[
        "Isaksen,\u00a0Magnar",
        "10/13/1910"
    ],
    "ISAKSPRE01":[
        "Isaksson,\u00a0Preben",
        "1/22/1943"
    ],
    "ISAOKRYO01":[
        "Isaoka,\u00a0Ryoji",
        "2/18/1962"
    ],
    "ISAREAND01":[
        "Isarescu,\u00a0Andreea",
        "7/3/1984"
    ],
    "ISASIJOE01":[
        "Isasi,\u00a0Joel",
        "7/31/1967"
    ],
    "ISASZR%D3B01":[
        "Isaszegi,\u00a0R\u00f3bert",
        "5/2/1965"
    ],
    "ISAYEANA01":[
        "Isayev,\u00a0Anatoly",
        "7/14/1932"
    ],
    "ISBERPAU01":[
        "Isberg,\u00a0Paul",
        "9/2/1882"
    ],
    "ISHCHMIK01":[
        "Ishchenko,\u00a0Mikhail",
        "5/19/1950"
    ],
    "ISHIDKYO01":[
        "Ishida,\u00a0Kyoko",
        "7/12/1960"
    ],
    "ISHIHTAT01":[
        "Ishihara,\u00a0Tatsuyoshi",
        "3/24/1964"
    ],
    "ISHIICHI01":[
        "Ishii,\u00a0Chiaki",
        "10/1/1941"
    ],
    "ISHIIHIR01":[
        "Ishii,\u00a0Hiroshi",
        "9/21/1939"
    ],
    "ISHIIHIR02":[
        "Ishii,\u00a0Hirotoshi",
        "9/14/1977"
    ],
    "ISHIISHO01":[
        "Ishii,\u00a0Shohachi",
        "9/20/1926"
    ],
    "ISHIKTAE01":[
        "Ishikawa,\u00a0Taeko",
        "10/14/1975"
    ],
    "ISHIMTAK01":[
        "Ishimoto,\u00a0Takashi",
        "4/6/1935"
    ],
    "ISHMOSVE01":[
        "Ishmouratova,\u00a0Svetlana",
        "4/20/1972"
    ],
    "ISHOYCYN01":[
        "Ishoy,\u00a0Cynthia",
        "6/19/1952"
    ],
    "ISINBYEL01":[
        "Isinbayeva,\u00a0Yelena",
        "6/3/1982"
    ],
    "ISKANMNA01":[
        "Iskandaryan,\u00a0Mnatsakan",
        "5/17/1967"
    ],
    "ISLAMAKH01":[
        "Islam,\u00a0Akhtarul",
        "1/1/1947"
    ],
    "ISLERJEN01":[
        "Isler,\u00a0Jennifer",
        "12/1/1963"
    ],
    "ISMAE01":[
        "Ismael,\u00a0",
        "2/7/1977"
    ],
    "ISMAIAHM01":[
        "Ismail,\u00a0Ahmed",
        "10/21/1975"
    ],
    "ISMAISIM01":[
        "Ismailciuc,\u00a0Simion",
        "7/13/1930"
    ],
    "ISMAYRUD01":[
        "Ismayr,\u00a0Rudolf",
        "10/14/1908"
    ],
    "ISOBESAT01":[
        "Isobe,\u00a0Sata",
        "12/19/1944"
    ],
    "ISODAYOK01":[
        "Isoda,\u00a0Yoko",
        "8/26/1978"
    ],
    "ISOHOVOL01":[
        "Iso-Hollo,\u00a0Volmari",
        "5/1/1907"
    ],
    "ISOMEJAR01":[
        "Isomets\u00e4,\u00a0Jari",
        "9/11/1968"
    ],
    "ISRA%CBISA01":[
        "Isra\u00ebls,\u00a0Isa\u00e4c",
        "2/3/1865"
    ],
    "ISRAESVE01":[
        "Israelsson,\u00a0Sven",
        "1/17/1920"
    ],
    "ISSELFER01":[
        "Issel\u00e9,\u00a0Fernand",
        "2/22/1915"
    ],
    "ISTADJON01":[
        "Istad,\u00a0Jon",
        "7/29/1939"
    ],
    "ISTOMYUR01":[
        "Istomin,\u00a0Yury",
        "7/10/1944"
    ],
    "ITOKAZ01":[
        "Ito,\u00a0Kazue",
        "12/22/1977"
    ],
    "ITOMID01":[
        "Ito,\u00a0Midori",
        "8/13/1969"
    ],
    "ITOTOM01":[
        "Ito,\u00a0Tomohito",
        "10/30/1970"
    ],
    "ITTEDG01":[
        "Itt,\u00a0Edgar",
        "6/8/1967"
    ],
    "IV%C1DYS%C1N01":[
        "Iv\u00e1dy,\u00a0S\u00e1ndor",
        "5/1/1903"
    ],
    "IVANEVYA01":[
        "Ivanenko,\u00a0Vyacheslav",
        "3/3/1961"
    ],
    "IVANIALE01":[
        "Ivanitsky,\u00a0Aleksandr",
        "12/8/1937"
    ],
    "IVANIGOR01":[
        "Ivanisevic,\u00a0Goran",
        "9/13/1971"
    ],
    "IVANOALE01":[
        "Ivanov,\u00a0Aleksandr",
        "1/10/1951"
    ],
    "IVANOBOR01":[
        "Ivanova,\u00a0Borislava",
        "11/24/1966"
    ],
    "IVANODIM01":[
        "Ivanov,\u00a0Dimitrie",
        "9/24/1944"
    ],
    "IVANOEDU01":[
        "Ivanov,\u00a0Eduard",
        "4/25/1938"
    ],
    "IVANOGEO01":[
        "Ivanov,\u00a0Georgi",
        "5/10/1947"
    ],
    "IVANOHAR01":[
        "Ivanov,\u00a0Haralambie",
        "2/23/1941"
    ],
    "IVANOIOU01":[
        "Ivanova,\u00a0Ioulia",
        "n/a"
    ],
    "IVANOIVA01":[
        "Ivanov,\u00a0Ivan",
        "8/27/1971"
    ],
    "IVANOKIR01":[
        "Ivanova,\u00a0Kira",
        "2/21/1963"
    ],
    "IVANOKIR02":[
        "Ivanov,\u00a0Kiril",
        "1/14/1960"
    ],
    "IVANOLID01":[
        "Ivanova-Kalinina,\u00a0Lidiya",
        "1/27/1937"
    ],
    "IVANOMIK01":[
        "Ivanov,\u00a0Mikhail",
        "4/18/1958"
    ],
    "IVANOMIK02":[
        "Ivanov,\u00a0Mikhail",
        "11/20/1977"
    ],
    "IVANONAT01":[
        "Ivanova,\u00a0Natalia",
        "9/1/1971"
    ],
    "IVANONIK01":[
        "Ivanov,\u00a0Nikolay",
        "8/20/1949"
    ],
    "IVANOOLI01":[
        "Ivanova,\u00a0Olimpiada",
        "5/5/1970"
    ],
    "IVANOPIE01":[
        "Ivanov,\u00a0Pietro",
        "n/a"
    ],
    "IVANOROM01":[
        "Ivanovskiy,\u00a0Roman",
        "n/a"
    ],
    "IVANOSTA01":[
        "Ivanov,\u00a0Stancho",
        "4/11/1937"
    ],
    "IVANOSVE01":[
        "Ivanov,\u00a0Svetoslav",
        "12/16/1951"
    ],
    "IVANOVAL01":[
        "Ivanov,\u00a0Valentin",
        "11/19/1934"
    ],
    "IVANOVAS01":[
        "Ivanov,\u00a0Vasily",
        "11/8/1972"
    ],
    "IVANOVIK01":[
        "Ivanov,\u00a0Viktor",
        "12/21/1930"
    ],
    "IVANOVIT01":[
        "Ivanov,\u00a0Vitaly",
        "2/3/1976"
    ],
    "IVANOVLA01":[
        "Ivanov,\u00a0Vladimir",
        "9/10/1940"
    ],
    "IVANOVYA01":[
        "Ivanov,\u00a0Vyacheslav",
        "4/30/1938"
    ],
    "IVANPAU01":[
        "Ivan,\u00a0Paula",
        "7/20/1963"
    ],
    "IVARSLAR01":[
        "Ivarsson,\u00a0Lars",
        "10/21/1963"
    ],
    "IVCHEYEV01":[
        "Ivchenko,\u00a0Yevgeny",
        "6/26/1938"
    ],
    "IVERSALL01":[
        "Iverson,\u00a0Allen",
        "6/7/1975"
    ],
    "IVERSBJA01":[
        "Iversen,\u00a0Bjarne",
        "10/2/1912"
    ],
    "IVERSOLE01":[
        "Iversen,\u00a0Ole",
        "2/21/1884"
    ],
    "IVESCLA01":[
        "Ives,\u00a0Clay",
        "9/5/1972"
    ],
    "IVESEDW01":[
        "Ives,\u00a0Edward",
        "1/3/1961"
    ],
    "IVEYMIT01":[
        "Ivey,\u00a0Mitchell",
        "2/2/1949"
    ],
    "IVIEBRY01":[
        "Ivie,\u00a0Bryan",
        "5/5/1969"
    ],
    "IVINSTAT01":[
        "Ivinskaya,\u00a0Tatyana",
        "3/27/1958"
    ],
    "IVKOVKIR01":[
        "Ivkov,\u00a0Kiril",
        "6/21/1946"
    ],
    "IVKOVTOM01":[
        "Ivkovic,\u00a0Tomislav",
        "8/11/1960"
    ],
    "IVKOVVLA01":[
        "Ivkovic,\u00a0Vlado",
        "7/25/1929"
    ],
    "IVOSEALE01":[
        "Ivosev,\u00a0Aleksandra",
        "3/17/1974"
    ],
    "IWABUYUM01":[
        "Iwabuchi,\u00a0Yumi",
        "9/10/1979"
    ],
    "IWAHATOY01":[
        "Iwahara,\u00a0Toyoko",
        "5/11/1945"
    ],
    "IWAKUHIS01":[
        "Iwakuma,\u00a0Hisashi",
        "4/12/1981"
    ],
    "IWASAKUN01":[
        "Iwasaki,\u00a0Kunihiro",
        "10/5/1944"
    ],
    "IWASAKYO01":[
        "Iwasaki,\u00a0Kyoko",
        "7/21/1978"
    ],
    "IWASEHIT01":[
        "Iwase,\u00a0Hitoki",
        "11/10/1974"
    ],
    "IZAGUSIL01":[
        "Izaguirre,\u00a0Silverio",
        "8/31/1897"
    ],
    "IZONRDAV01":[
        "Izonritei,\u00a0David",
        "4/29/1963"
    ],
    "IZQUILIL01":[
        "Izquierdo,\u00a0Lilia",
        "2/20/1967"
    ],
    "IZUMIHIR01":[
        "Izumi,\u00a0Hiroshi",
        "6/22/1982"
    ],
    "IbsenMar01":[
        "Ibsen,\u00a0Martin",
        "n/a"
    ],
    "IdokoFra01":[
        "Idoko,\u00a0Franca",
        "6/15/1985"
    ],
    "IdowuPhi01":[
        "Idowu,\u00a0Phillips",
        "n/a"
    ],
    "IglesRon01":[
        "Iglesias,\u00a0Roniel",
        "n/a"
    ],
    "IlcheLar01":[
        "Ilchenko,\u00a0Larisa",
        "n/a"
    ],
    "IlinIly01":[
        "Ilin,\u00a0Ilya",
        "n/a"
    ],
    "ImJeoCho01":[
        "Im-Jeong,\u00a0Choi",
        "2/14/1981"
    ],
    "ImranSha01":[
        "Imranov,\u00a0Shahin",
        "n/a"
    ],
    "IngebTom01":[
        "Ingebrigtsen,\u00a0Tommy",
        "8/8/1977"
    ],
    "IngimIng01":[
        "Ingimundarson,\u00a0Ingimundur",
        "1/1/1900"
    ],
    "InmanJos01":[
        "Inman,\u00a0Josh",
        "3/13/1980"
    ],
    "InsalKim01":[
        "Insalaco\u00a0,\u00a0Kim",
        "11/4/1980"
    ],
    "IsaacPro01":[
        "Isaac,\u00a0Promise",
        "12/2/1987"
    ],
    "IsaccJen01":[
        "Isacco,\u00a0Jennifer",
        "2/27/1977"
    ],
    "IsakoSar01":[
        "Isakovic,\u00a0Sara",
        "n/a"
    ],
    "IshchNat01":[
        "Ishchenko,\u00a0Natalia",
        "4/8/1986"
    ],
    "IshiiSat01":[
        "Ishii,\u00a0Satoshi",
        "n/a"
    ],
    "IsmaiHal01":[
        "Ismaila,\u00a0Halimat",
        "7/3/1984"
    ],
    "ItoSac01":[
        "Ito,\u00a0Sachiko",
        "10/11/1975"
    ],
    "IvankAna01":[
        "Ivankova,\u00a0Anastasia",
        "11/22/1991"
    ],
    "IzbasSan01":[
        "Izbasa,\u00a0Sandra",
        "n/a"
    ],
    "IzotoDan01":[
        "Izotov,\u00a0Danila",
        "1/1/1900"
    ],
    "IzykoAle01":[
        "Izykowski,\u00a0Alex",
        "1/26/1984"
    ]
}