[
    {
        "athlete":"jamie-staff",
        "event":"team-sprint-men",
        "medal":"G",
        "olympics":"beijing-2008",
        "result":"",
        "sport":"cycling"
    },
    {
        "athlete":"asier-maeztu-billelabeitia",
        "event":"team-pursuit-(4000m)-men",
        "medal":"B",
        "olympics":"athens-2004",
        "result":"",
        "sport":"cycling"
    },
    {
        "athlete":"luke-roberts",
        "event":"team-pursuit-(4000m)-men",
        "medal":"G",
        "olympics":"athens-2004",
        "result":"",
        "sport":"cycling"
    },
    {
        "athlete":"graeme-brown",
        "event":"team-pursuit-(4000m)-men",
        "medal":"G",
        "olympics":"athens-2004",
        "result":"",
        "sport":"cycling"
    },
    {
        "athlete":"graeme-brown",
        "event":"madison-men",
        "medal":"G",
        "olympics":"athens-2004",
        "result":"22",
        "sport":"cycling"
    },
    {
        "athlete":"alex-rasmussen",
        "event":"team-pursuit-(4000m)-men",
        "medal":"S",
        "olympics":"beijing-2008",
        "result":"",
        "sport":"cycling"
    },
    {
        "athlete":"jens-erik-madsen",
        "event":"team-pursuit-(4000m)-men",
        "medal":"S",
        "olympics":"beijing-2008",
        "result":"",
        "sport":"cycling"
    },
    {
        "athlete":"casper-joergensen",
        "event":"team-pursuit-(4000m)-men",
        "medal":"S",
        "olympics":"beijing-2008",
        "result":"",
        "sport":"cycling"
    },
    {
        "athlete":"michael-faerk-christensen",
        "event":"team-pursuit-(4000m)-men",
        "medal":"S",
        "olympics":"beijing-2008",
        "result":"",
        "sport":"cycling"
    },
    {
        "athlete":"paul-manning",
        "event":"team-pursuit-(4000m)-men",
        "medal":"G",
        "olympics":"beijing-2008",
        "result":"",
        "sport":"cycling"
    },
    {
        "athlete":"paul-manning",
        "event":"team-pursuit-(4000m)-men",
        "medal":"S",
        "olympics":"athens-2004",
        "result":"",
        "sport":"cycling"
    },
    {
        "athlete":"paul-manning",
        "event":"team-pursuit-(4000m)-men",
        "medal":"B",
        "olympics":"sydney-2000",
        "result":"",
        "sport":"cycling"
    },
    {
        "athlete":"theo-bos",
        "event":"sprint-individual-men",
        "medal":"S",
        "olympics":"athens-2004",
        "result":"",
        "sport":"cycling"
    },
    {
        "athlete":"kiyofumi-nagai",
        "event":"keirin-men",
        "medal":"B",
        "olympics":"beijing-2008",
        "result":"",
        "sport":"cycling"
    },
    {
        "athlete":"brett-lancaster",
        "event":"team-pursuit-(4000m)-men",
        "medal":"G",
        "olympics":"athens-2004",
        "result":"",
        "sport":"cycling"
    },
    {
        "athlete":"antonio-tauler",
        "event":"madison-men",
        "medal":"S",
        "olympics":"beijing-2008",
        "result":"",
        "sport":"cycling"
    },
    {
        "athlete":"pierre-trentin",
        "event":"sprint-individual-men",
        "medal":"B",
        "olympics":"mexico-1968",
        "result":"",
        "sport":"cycling"
    },
    {
        "athlete":"pierre-trentin",
        "event":"1km-time-trial-men",
        "medal":"G",
        "olympics":"mexico-1968",
        "result":"1:03.91    (56.3 km/h)",
        "sport":"cycling"
    },
    {
        "athlete":"pierre-trentin",
        "event":"2000m-tandem-men",
        "medal":"G",
        "olympics":"mexico-1968",
        "result":"",
        "sport":"cycling"
    },
    {
        "athlete":"pierre-trentin",
        "event":"1km-time-trial-men",
        "medal":"B",
        "olympics":"tokyo-1964",
        "result":"1:10.42    (51.121)",
        "sport":"cycling"
    },
    {
        "athlete":"daniel-clark",
        "event":"1km-time-trial-men",
        "medal":"S",
        "olympics":"munich-1972",
        "result":"1:06.87   (53.835 km/h)",
        "sport":"cycling"
    },
    {
        "athlete":"janusz-kierzkowski",
        "event":"1km-time-trial-men",
        "medal":"B",
        "olympics":"mexico-1968",
        "result":"1:04.63    (55.7 km/h)",
        "sport":"cycling"
    },
    {
        "athlete":"michel-vaarten",
        "event":"1km-time-trial-men",
        "medal":"S",
        "olympics":"montreal-1976",
        "result":"1:07.516   (53.321)",
        "sport":"cycling"
    },
    {
        "athlete":"klaus-jurgen-grunke",
        "event":"1km-time-trial-men",
        "medal":"G",
        "olympics":"montreal-1976",
        "result":"1:05.927   (54.606)",
        "sport":"cycling"
    },
    {
        "athlete":"jurgen-schutze",
        "event":"1km-time-trial-men",
        "medal":"B",
        "olympics":"munich-1972",
        "result":"1:07.02   (53.715 km/h)",
        "sport":"cycling"
    },
    {
        "athlete":"niels-christian-fredborg",
        "event":"1km-time-trial-men",
        "medal":"B",
        "olympics":"montreal-1976",
        "result":"1:07.617   (53.241)",
        "sport":"cycling"
    },
    {
        "athlete":"niels-christian-fredborg",
        "event":"1km-time-trial-men",
        "medal":"G",
        "olympics":"munich-1972",
        "result":"1:06.44   (54.184 km/h)",
        "sport":"cycling"
    },
    {
        "athlete":"niels-christian-fredborg",
        "event":"1km-time-trial-men",
        "medal":"S",
        "olympics":"mexico-1968",
        "result":"1:04.61    (55.7 km/h)",
        "sport":"cycling"
    },
    {
        "athlete":"giovanni-pettenella",
        "event":"sprint-individual-men",
        "medal":"G",
        "olympics":"tokyo-1964",
        "result":"",
        "sport":"cycling"
    },
    {
        "athlete":"giovanni-pettenella",
        "event":"1km-time-trial-men",
        "medal":"S",
        "olympics":"tokyo-1964",
        "result":"1:10.09    (51.362)",
        "sport":"cycling"
    },
    {
        "athlete":"valentino-gasparella",
        "event":"sprint-individual-men",
        "medal":"B",
        "olympics":"rome-1960",
        "result":"",
        "sport":"cycling"
    },
    {
        "athlete":"valentino-gasparella",
        "event":"team-pursuit-(4000m)-men",
        "medal":"G",
        "olympics":"melbourne-stockholm-1956",
        "result":"4:37.4",
        "sport":"cycling"
    },
    {
        "athlete":"sante-gaiardoni",
        "event":"1km-time-trial-men",
        "medal":"G",
        "olympics":"rome-1960",
        "result":"1:07.27",
        "sport":"cycling"
    },
    {
        "athlete":"sante-gaiardoni",
        "event":"sprint-individual-men",
        "medal":"G",
        "olympics":"rome-1960",
        "result":"",
        "sport":"cycling"
    },
    {
        "athlete":"rostislav-vargashkin",
        "event":"1km-time-trial-men",
        "medal":"B",
        "olympics":"rome-1960",
        "result":"1:08.86",
        "sport":"cycling"
    },
    {
        "athlete":"dieter-gieseler",
        "event":"1km-time-trial-men",
        "medal":"S",
        "olympics":"rome-1960",
        "result":"1:08.75",
        "sport":"cycling"
    },
    {
        "athlete":"patrick-sercu",
        "event":"1km-time-trial-men",
        "medal":"G",
        "olympics":"tokyo-1964",
        "result":"1:09.59    (51.731)",
        "sport":"cycling"
    },
    {
        "athlete":"leif-mortensen",
        "event":"individual-road-race-men",
        "medal":"S",
        "olympics":"mexico-1968",
        "result":"4:42:49.71  (41.624)",
        "sport":"cycling"
    },
    {
        "athlete":"rene-marinus-pijnen",
        "event":"team-time-trial-men",
        "medal":"G",
        "olympics":"mexico-1968",
        "result":"2:07:49.06  (47.881)",
        "sport":"cycling"
    },
    {
        "athlete":"gosta-pettersson",
        "event":"individual-road-race-men",
        "medal":"B",
        "olympics":"mexico-1968",
        "result":"4:43:15.24  (41.560)",
        "sport":"cycling"
    },
    {
        "athlete":"gosta-pettersson",
        "event":"team-time-trial-men",
        "medal":"S",
        "olympics":"mexico-1968",
        "result":"2:09:26.60  (46.355)",
        "sport":"cycling"
    },
    {
        "athlete":"gosta-pettersson",
        "event":"team-time-trial-men",
        "medal":"B",
        "olympics":"tokyo-1964",
        "result":"2:27:11.52  (44.795)",
        "sport":"cycling"
    },
    {
        "athlete":"mario-zanin",
        "event":"individual-road-race-men",
        "medal":"G",
        "olympics":"tokyo-1964",
        "result":"4:39:51.63  (41.770)",
        "sport":"cycling"
    },
    {
        "athlete":"walter-godefroot",
        "event":"individual-road-race-men",
        "medal":"B",
        "olympics":"tokyo-1964",
        "result":"4:39:51.74  (41.770)",
        "sport":"cycling"
    },
    {
        "athlete":"kjeld-akerstrom-rodian",
        "event":"individual-road-race-men",
        "medal":"S",
        "olympics":"tokyo-1964",
        "result":"4:39:51.65  (41.770)",
        "sport":"cycling"
    },
    {
        "athlete":"pierfranco-vianelli",
        "event":"individual-road-race-men",
        "medal":"G",
        "olympics":"mexico-1968",
        "result":"4:41:25.24  (41.831)",
        "sport":"cycling"
    },
    {
        "athlete":"pierfranco-vianelli",
        "event":"team-time-trial-men",
        "medal":"B",
        "olympics":"mexico-1968",
        "result":"2:10:18.74  (46.047)",
        "sport":"cycling"
    },
    {
        "athlete":"preben-isaksson",
        "event":"individual-pursuit-men",
        "medal":"B",
        "olympics":"tokyo-1964",
        "result":"",
        "sport":"cycling"
    },
    {
        "athlete":"viktor-logunov",
        "event":"2000m-tandem-men",
        "medal":"S",
        "olympics":"tokyo-1964",
        "result":"",
        "sport":"cycling"
    },
    {
        "athlete":"lothar-claesges",
        "event":"team-pursuit-(4000m)-men",
        "medal":"G",
        "olympics":"tokyo-1964",
        "result":"",
        "sport":"cycling"
    },
    {
        "athlete":"peter-vonhof",
        "event":"team-pursuit-(4000m)-men",
        "medal":"G",
        "olympics":"montreal-1976",
        "result":"",
        "sport":"cycling"
    },
    {
        "athlete":"peter-vonhof",
        "event":"team-pursuit-(4000m)-men",
        "medal":"G",
        "olympics":"munich-1972",
        "result":"",
        "sport":"cycling"
    },
    {
        "athlete":"gunther-schumacher",
        "event":"team-pursuit-(4000m)-men",
        "medal":"G",
        "olympics":"montreal-1976",
        "result":"",
        "sport":"cycling"
    },
    {
        "athlete":"gunther-schumacher",
        "event":"team-pursuit-(4000m)-men",
        "medal":"G",
        "olympics":"munich-1972",
        "result":"",
        "sport":"cycling"
    },
    {
        "athlete":"jens-lehmann",
        "event":"team-pursuit-(4000m)-men",
        "medal":"G",
        "olympics":"sydney-2000",
        "result":"",
        "sport":"cycling"
    },
    {
        "athlete":"jens-lehmann",
        "event":"individual-pursuit-men",
        "medal":"S",
        "olympics":"sydney-2000",
        "result":"",
        "sport":"cycling"
    },
    {
        "athlete":"jens-lehmann",
        "event":"team-pursuit-(4000m)-men",
        "medal":"G",
        "olympics":"barcelona-1992",
        "result":"4:08.791",
        "sport":"cycling"
    },
    {
        "athlete":"jens-lehmann",
        "event":"individual-pursuit-men",
        "medal":"S",
        "olympics":"barcelona-1992",
        "result":"4:30.054",
        "sport":"cycling"
    },
    {
        "athlete":"aristidis-konstantinidis",
        "event":"individual-road-race-men",
        "medal":"G",
        "olympics":"athens-1896",
        "result":"3:22:31,0",
        "sport":"cycling"
    },
    {
        "athlete":"august-goedrich",
        "event":"individual-road-race-men",
        "medal":"S",
        "olympics":"athens-1896",
        "result":"3:42:18,0",
        "sport":"cycling"
    },
    {
        "athlete":"edward-battel",
        "event":"individual-road-race-men",
        "medal":"B",
        "olympics":"athens-1896",
        "result":"",
        "sport":"cycling"
    },
    {
        "athlete":"harry-ryan",
        "event":"sprint-individual-men",
        "medal":"B",
        "olympics":"antwerp-1920",
        "result":"",
        "sport":"cycling"
    },
    {
        "athlete":"harry-ryan",
        "event":"2000m-tandem-men",
        "medal":"G",
        "olympics":"antwerp-1920",
        "result":"2:49.4",
        "sport":"cycling"
    },
    {
        "athlete":"albert-white",
        "event":"team-pursuit-(4000m)-men",
        "medal":"S",
        "olympics":"antwerp-1920",
        "result":"",
        "sport":"cycling"
    },
    {
        "athlete":"horace-thomas-johnson",
        "event":"sprint-individual-men",
        "medal":"S",
        "olympics":"antwerp-1920",
        "result":"",
        "sport":"cycling"
    },
    {
        "athlete":"horace-thomas-johnson",
        "event":"team-pursuit-(4000m)-men",
        "medal":"S",
        "olympics":"antwerp-1920",
        "result":"",
        "sport":"cycling"
    },
    {
        "athlete":"horace-thomas-johnson",
        "event":"2000m-tandem-men",
        "medal":"S",
        "olympics":"london-1908",
        "result":"",
        "sport":"cycling"
    },
    {
        "athlete":"piet-ikelaar",
        "event":"50km-men",
        "medal":"B",
        "olympics":"antwerp-1920",
        "result":"",
        "sport":"cycling"
    },
    {
        "athlete":"piet-ikelaar",
        "event":"2000m-tandem-men",
        "medal":"B",
        "olympics":"antwerp-1920",
        "result":"",
        "sport":"cycling"
    },
    {
        "athlete":"harry-stenqvist",
        "event":"individual-time-trial-men",
        "medal":"G",
        "olympics":"antwerp-1920",
        "result":"4:40:01.8",
        "sport":"cycling"
    },
    {
        "athlete":"harry-stenqvist",
        "event":"team-time-trial-men",
        "medal":"S",
        "olympics":"antwerp-1920",
        "result":"19:23:10.0",
        "sport":"cycling"
    },
    {
        "athlete":"albert-de-bunne",
        "event":"team-time-trial-men",
        "medal":"B",
        "olympics":"antwerp-1920",
        "result":"19:28:44.4",
        "sport":"cycling"
    },
    {
        "athlete":"jean-janssens",
        "event":"team-time-trial-men",
        "medal":"B",
        "olympics":"antwerp-1920",
        "result":"19:28:44.4",
        "sport":"cycling"
    },
    {
        "athlete":"fernand-canteloube",
        "event":"team-time-trial-men",
        "medal":"G",
        "olympics":"antwerp-1920",
        "result":"19:16:43.2",
        "sport":"cycling"
    },
    {
        "athlete":"fernand-canteloube",
        "event":"individual-time-trial-men",
        "medal":"B",
        "olympics":"antwerp-1920",
        "result":"4:42:54.4",
        "sport":"cycling"
    },
    {
        "athlete":"henry-justaves-kaltenbrun",
        "event":"team-pursuit-(4000m)-men",
        "medal":"B",
        "olympics":"antwerp-1920",
        "result":"",
        "sport":"cycling"
    },
    {
        "athlete":"henry-justaves-kaltenbrun",
        "event":"individual-time-trial-men",
        "medal":"S",
        "olympics":"antwerp-1920",
        "result":"4:41:26.6",
        "sport":"cycling"
    },
    {
        "athlete":"jacobus-willems",
        "event":"50km-men",
        "medal":"G",
        "olympics":"paris-1924",
        "result":"1:18:24.0",
        "sport":"cycling"
    },
    {
        "athlete":"jozef-lange",
        "event":"team-pursuit-(4000m)-men",
        "medal":"S",
        "olympics":"paris-1924",
        "result":"",
        "sport":"cycling"
    },
    {
        "athlete":"gerard-bosch-van-drakestein",
        "event":"1km-time-trial-men",
        "medal":"S",
        "olympics":"amsterdam-1928",
        "result":"1:15.1",
        "sport":"cycling"
    },
    {
        "athlete":"gerard-bosch-van-drakestein",
        "event":"2000m-tandem-men",
        "medal":"B",
        "olympics":"paris-1924",
        "result":"",
        "sport":"cycling"
    },
    {
        "athlete":"victor-johnson",
        "event":"one-lap-(660y)-sprint-men",
        "medal":"G",
        "olympics":"london-1908",
        "result":"51.2",
        "sport":"cycling"
    },
    {
        "athlete":"maurice-schilles",
        "event":"2000m-tandem-men",
        "medal":"G",
        "olympics":"london-1908",
        "result":"3:07.1",
        "sport":"cycling"
    },
    {
        "athlete":"maurice-schilles",
        "event":"5000m-men",
        "medal":"S",
        "olympics":"london-1908",
        "result":"",
        "sport":"cycling"
    },
    {
        "athlete":"andre-auffray",
        "event":"2000m-tandem-men",
        "medal":"G",
        "olympics":"london-1908",
        "result":"3:07.1",
        "sport":"cycling"
    },
    {
        "athlete":"andre-auffray",
        "event":"5000m-men",
        "medal":"B",
        "olympics":"london-1908",
        "result":"",
        "sport":"cycling"
    },
    {
        "athlete":"karl-neumer",
        "event":"1980-yards-pursuit,-team-men",
        "medal":"S",
        "olympics":"london-1908",
        "result":"2:28.6",
        "sport":"cycling"
    },
    {
        "athlete":"karl-neumer",
        "event":"one-lap-(660y)-sprint-men",
        "medal":"B",
        "olympics":"london-1908",
        "result":"",
        "sport":"cycling"
    },
    {
        "athlete":"emile-demangel",
        "event":"one-lap-(660y)-sprint-men",
        "medal":"S",
        "olympics":"london-1908",
        "result":"",
        "sport":"cycling"
    },
    {
        "athlete":"benjamin-jones",
        "event":"20km-men",
        "medal":"S",
        "olympics":"london-1908",
        "result":"",
        "sport":"cycling"
    },
    {
        "athlete":"benjamin-jones",
        "event":"5000m-men",
        "medal":"G",
        "olympics":"london-1908",
        "result":"8:36.2",
        "sport":"cycling"
    },
    {
        "athlete":"benjamin-jones",
        "event":"1980-yards-pursuit,-team-men",
        "medal":"G",
        "olympics":"london-1908",
        "result":"2:18.6",
        "sport":"cycling"
    },
    {
        "athlete":"clarence-kingsbury",
        "event":"20km-men",
        "medal":"G",
        "olympics":"london-1908",
        "result":"34:13.6",
        "sport":"cycling"
    },
    {
        "athlete":"clarence-kingsbury",
        "event":"1980-yards-pursuit,-team-men",
        "medal":"G",
        "olympics":"london-1908",
        "result":"2:18.6",
        "sport":"cycling"
    },
    {
        "athlete":"willy-falck-hansen",
        "event":"1km-time-trial-men",
        "medal":"G",
        "olympics":"amsterdam-1928",
        "result":"1:14.2",
        "sport":"cycling"
    },
    {
        "athlete":"willy-falck-hansen",
        "event":"1km-pursuit-men",
        "medal":"B",
        "olympics":"amsterdam-1928",
        "result":"",
        "sport":"cycling"
    },
    {
        "athlete":"willy-falck-hansen",
        "event":"1km-pursuit-men",
        "medal":"B",
        "olympics":"amsterdam-1928",
        "result":"",
        "sport":"cycling"
    },
    {
        "athlete":"willy-falck-hansen",
        "event":"2000m-tandem-men",
        "medal":"S",
        "olympics":"paris-1924",
        "result":"",
        "sport":"cycling"
    },
    {
        "athlete":"roger-beaufrand",
        "event":"1km-pursuit-men",
        "medal":"G",
        "olympics":"amsterdam-1928",
        "result":"",
        "sport":"cycling"
    },
    {
        "athlete":"roger-beaufrand",
        "event":"1km-pursuit-men",
        "medal":"G",
        "olympics":"amsterdam-1928",
        "result":"",
        "sport":"cycling"
    },
    {
        "athlete":"antonius-hendrikus-mazairac",
        "event":"1km-pursuit-men",
        "medal":"S",
        "olympics":"amsterdam-1928",
        "result":"",
        "sport":"cycling"
    },
    {
        "athlete":"antonius-hendrikus-mazairac",
        "event":"1km-pursuit-men",
        "medal":"S",
        "olympics":"amsterdam-1928",
        "result":"",
        "sport":"cycling"
    },
    {
        "athlete":"angelo-de-martino",
        "event":"team-pursuit-(4000m)-men",
        "medal":"G",
        "olympics":"paris-1924",
        "result":"5:15.0",
        "sport":"cycling"
    },
    {
        "athlete":"armand-blanchonnet",
        "event":"team-time-trial-men",
        "medal":"G",
        "olympics":"paris-1924",
        "result":"19:30:14.0",
        "sport":"cycling"
    },
    {
        "athlete":"armand-blanchonnet",
        "event":"individual-road-race-men",
        "medal":"G",
        "olympics":"paris-1924",
        "result":"6:20:48.0",
        "sport":"cycling"
    },
    {
        "athlete":"gunnar-skold",
        "event":"team-time-trial-men",
        "medal":"B",
        "olympics":"paris-1924",
        "result":"19:59:41.6",
        "sport":"cycling"
    },
    {
        "athlete":"rene-hamel",
        "event":"team-time-trial-men",
        "medal":"G",
        "olympics":"paris-1924",
        "result":"19:30:14.0",
        "sport":"cycling"
    },
    {
        "athlete":"rene-hamel",
        "event":"individual-road-race-men",
        "medal":"B",
        "olympics":"paris-1924",
        "result":"6:30:51.6",
        "sport":"cycling"
    },
    {
        "athlete":"henri-hoevenaers",
        "event":"team-time-trial-men",
        "medal":"S",
        "olympics":"paris-1924",
        "result":"19:46:55.6",
        "sport":"cycling"
    },
    {
        "athlete":"henri-hoevenaers",
        "event":"individual-road-race-men",
        "medal":"S",
        "olympics":"paris-1924",
        "result":"6:30:27.0",
        "sport":"cycling"
    },
    {
        "athlete":"henri-hoevenaers",
        "event":"team-pursuit-(4000m)-men",
        "medal":"B",
        "olympics":"paris-1924",
        "result":"",
        "sport":"cycling"
    },
    {
        "athlete":"cyril-alden",
        "event":"50km-men",
        "medal":"S",
        "olympics":"paris-1924",
        "result":"",
        "sport":"cycling"
    },
    {
        "athlete":"cyril-alden",
        "event":"50km-men",
        "medal":"S",
        "olympics":"antwerp-1920",
        "result":"",
        "sport":"cycling"
    },
    {
        "athlete":"cyril-alden",
        "event":"team-pursuit-(4000m)-men",
        "medal":"S",
        "olympics":"antwerp-1920",
        "result":"",
        "sport":"cycling"
    },
    {
        "athlete":"henry-george",
        "event":"50km-men",
        "medal":"G",
        "olympics":"antwerp-1920",
        "result":"1:16:43.2",
        "sport":"cycling"
    },
    {
        "athlete":"ruggero-ferrario",
        "event":"team-pursuit-(4000m)-men",
        "medal":"G",
        "olympics":"antwerp-1920",
        "result":"",
        "sport":"cycling"
    },
    {
        "athlete":"maurice-peeters",
        "event":"2000m-tandem-men",
        "medal":"B",
        "olympics":"paris-1924",
        "result":"",
        "sport":"cycling"
    },
    {
        "athlete":"maurice-peeters",
        "event":"sprint-individual-men",
        "medal":"G",
        "olympics":"antwerp-1920",
        "result":"1:38.3",
        "sport":"cycling"
    },
    {
        "athlete":"william-smith-4",
        "event":"2000m-tandem-men",
        "medal":"S",
        "olympics":"antwerp-1920",
        "result":"",
        "sport":"cycling"
    },
    {
        "athlete":"william-smith-4",
        "event":"team-pursuit-(4000m)-men",
        "medal":"B",
        "olympics":"antwerp-1920",
        "result":"",
        "sport":"cycling"
    },
    {
        "athlete":"jock-stewart",
        "event":"team-pursuit-(4000m)-men",
        "medal":"S",
        "olympics":"antwerp-1920",
        "result":"",
        "sport":"cycling"
    },
    {
        "athlete":"primo-magnani",
        "event":"team-pursuit-(4000m)-men",
        "medal":"G",
        "olympics":"antwerp-1920",
        "result":"",
        "sport":"cycling"
    },
    {
        "athlete":"james-walker-4",
        "event":"2000m-tandem-men",
        "medal":"S",
        "olympics":"antwerp-1920",
        "result":"",
        "sport":"cycling"
    },
    {
        "athlete":"james-walker-4",
        "event":"team-pursuit-(4000m)-men",
        "medal":"B",
        "olympics":"antwerp-1920",
        "result":"",
        "sport":"cycling"
    },
    {
        "athlete":"werner-potzernheim",
        "event":"sprint-individual-men",
        "medal":"B",
        "olympics":"helsinki-1952",
        "result":"",
        "sport":"cycling"
    },
    {
        "athlete":"lionel-cox",
        "event":"2000m-tandem-men",
        "medal":"G",
        "olympics":"helsinki-1952",
        "result":"",
        "sport":"cycling"
    },
    {
        "athlete":"lionel-cox",
        "event":"sprint-individual-men",
        "medal":"S",
        "olympics":"helsinki-1952",
        "result":"",
        "sport":"cycling"
    },
    {
        "athlete":"enzo-sacchi",
        "event":"sprint-individual-men",
        "medal":"G",
        "olympics":"helsinki-1952",
        "result":"12.0",
        "sport":"cycling"
    },
    {
        "athlete":"jean-cugnot",
        "event":"2000m-tandem-men",
        "medal":"G",
        "olympics":"paris-1924",
        "result":"12.6",
        "sport":"cycling"
    },
    {
        "athlete":"jean-cugnot",
        "event":"sprint-individual-men",
        "medal":"B",
        "olympics":"paris-1924",
        "result":"",
        "sport":"cycling"
    },
    {
        "athlete":"jacob-meijer",
        "event":"sprint-individual-men",
        "medal":"S",
        "olympics":"paris-1924",
        "result":"",
        "sport":"cycling"
    },
    {
        "athlete":"lucien-michard",
        "event":"sprint-individual-men",
        "medal":"G",
        "olympics":"paris-1924",
        "result":"12.8",
        "sport":"cycling"
    },
    {
        "athlete":"jan-lazarski",
        "event":"team-pursuit-(4000m)-men",
        "medal":"S",
        "olympics":"paris-1924",
        "result":"",
        "sport":"cycling"
    },
    {
        "athlete":"tomasz-stankiewicz",
        "event":"team-pursuit-(4000m)-men",
        "medal":"S",
        "olympics":"paris-1924",
        "result":"",
        "sport":"cycling"
    },
    {
        "athlete":"lucien-choury",
        "event":"2000m-tandem-men",
        "medal":"G",
        "olympics":"paris-1924",
        "result":"12.6",
        "sport":"cycling"
    },
    {
        "athlete":"edmund-hansen",
        "event":"2000m-tandem-men",
        "medal":"S",
        "olympics":"paris-1924",
        "result":"",
        "sport":"cycling"
    },
    {
        "athlete":"henry-hansen",
        "event":"team-time-trial-men",
        "medal":"G",
        "olympics":"amsterdam-1928",
        "result":"15:09:14",
        "sport":"cycling"
    },
    {
        "athlete":"henry-hansen",
        "event":"individual-time-trial-men",
        "medal":"G",
        "olympics":"amsterdam-1928",
        "result":"4:47:18",
        "sport":"cycling"
    },
    {
        "athlete":"bernhard-britz",
        "event":"individual-time-trial-men",
        "medal":"B",
        "olympics":"los-angeles-1932",
        "result":"2:29:45.2",
        "sport":"cycling"
    },
    {
        "athlete":"guglielmo-segato",
        "event":"individual-time-trial-men",
        "medal":"S",
        "olympics":"los-angeles-1932",
        "result":"2:29:21.4",
        "sport":"cycling"
    },
    {
        "athlete":"attilio-pavesi",
        "event":"individual-time-trial-men",
        "medal":"G",
        "olympics":"los-angeles-1932",
        "result":"2:28:05.6",
        "sport":"cycling"
    },
    {
        "athlete":"leonard-daghelinckx",
        "event":"team-pursuit-(4000m)-men",
        "medal":"B",
        "olympics":"paris-1924",
        "result":"",
        "sport":"cycling"
    },
    {
        "athlete":"alfredo-dinale",
        "event":"team-pursuit-(4000m)-men",
        "medal":"G",
        "olympics":"paris-1924",
        "result":"5:15.0",
        "sport":"cycling"
    },
    {
        "athlete":"marty-nothstein",
        "event":"sprint-individual-men",
        "medal":"G",
        "olympics":"sydney-2000",
        "result":"",
        "sport":"cycling"
    },
    {
        "athlete":"marty-nothstein",
        "event":"sprint-individual-men",
        "medal":"S",
        "olympics":"atlanta-1996",
        "result":"",
        "sport":"cycling"
    },
    {
        "athlete":"oksana-grishina",
        "event":"sprint-women",
        "medal":"S",
        "olympics":"sydney-2000",
        "result":"",
        "sport":"cycling"
    },
    {
        "athlete":"iryna-yanovych",
        "event":"sprint-women",
        "medal":"B",
        "olympics":"sydney-2000",
        "result":"",
        "sport":"cycling"
    },
    {
        "athlete":"mari-holden",
        "event":"individual-time-trial-women",
        "medal":"S",
        "olympics":"sydney-2000",
        "result":"42:37",
        "sport":"cycling"
    },
    {
        "athlete":"diana-ziliute",
        "event":"individual-road-race-women",
        "medal":"B",
        "olympics":"sydney-2000",
        "result":"03h06:31",
        "sport":"cycling"
    },
    {
        "athlete":"jimmi-madsen",
        "event":"team-pursuit-(4000m)-men",
        "medal":"B",
        "olympics":"barcelona-1992",
        "result":"4:15.860",
        "sport":"cycling"
    },
    {
        "athlete":"christophe-capelle",
        "event":"team-pursuit-(4000m)-men",
        "medal":"G",
        "olympics":"atlanta-1996",
        "result":"",
        "sport":"cycling"
    },
    {
        "athlete":"matthew-gilmore",
        "event":"madison-men",
        "medal":"S",
        "olympics":"sydney-2000",
        "result":"22,0",
        "sport":"cycling"
    },
    {
        "athlete":"jonny-clay",
        "event":"team-pursuit-(4000m)-men",
        "medal":"B",
        "olympics":"sydney-2000",
        "result":"",
        "sport":"cycling"
    },
    {
        "athlete":"bruno-risi",
        "event":"madison-men",
        "medal":"S",
        "olympics":"athens-2004",
        "result":"15",
        "sport":"cycling"
    },
    {
        "athlete":"stuart-o-grady",
        "event":"madison-men",
        "medal":"G",
        "olympics":"athens-2004",
        "result":"22",
        "sport":"cycling"
    },
    {
        "athlete":"stuart-o-grady",
        "event":"team-pursuit-(4000m)-men",
        "medal":"B",
        "olympics":"atlanta-1996",
        "result":"",
        "sport":"cycling"
    },
    {
        "athlete":"stuart-o-grady",
        "event":"points-race-men",
        "medal":"B",
        "olympics":"atlanta-1996",
        "result":"Pts 27",
        "sport":"cycling"
    },
    {
        "athlete":"stuart-o-grady",
        "event":"team-pursuit-(4000m)-men",
        "medal":"S",
        "olympics":"barcelona-1992",
        "result":"4:10.218",
        "sport":"cycling"
    },
    {
        "athlete":"yvonne-mcgregor",
        "event":"individual-pursuit-women",
        "medal":"B",
        "olympics":"sydney-2000",
        "result":"",
        "sport":"cycling"
    },
    {
        "athlete":"imelda-chiappa",
        "event":"individual-road-race-women",
        "medal":"S",
        "olympics":"atlanta-1996",
        "result":"2:36:38",
        "sport":"cycling"
    },
    {
        "athlete":"michael-sandstod",
        "event":"team-pursuit-(4000m)-men",
        "medal":"B",
        "olympics":"barcelona-1992",
        "result":"4:15.860",
        "sport":"cycling"
    },
    {
        "athlete":"fabio-casartelli",
        "event":"individual-road-race-men",
        "medal":"G",
        "olympics":"barcelona-1992",
        "result":"4:35:21",
        "sport":"cycling"
    },
    {
        "athlete":"erik-dekker",
        "event":"individual-road-race-men",
        "medal":"S",
        "olympics":"barcelona-1992",
        "result":"4:35:22",
        "sport":"cycling"
    },
    {
        "athlete":"arturas-kasputis",
        "event":"team-pursuit-(4000m)-men",
        "medal":"G",
        "olympics":"seoul-1988",
        "result":"4:13.31     (56.847)",
        "sport":"cycling"
    },
    {
        "athlete":"dainis-ozols",
        "event":"individual-road-race-men",
        "medal":"B",
        "olympics":"barcelona-1992",
        "result":"4:35:24",
        "sport":"cycling"
    },
    {
        "athlete":"sergiy-matveyev",
        "event":"team-pursuit-(4000m)-men",
        "medal":"S",
        "olympics":"sydney-2000",
        "result":"",
        "sport":"cycling"
    },
    {
        "athlete":"michel-lafis",
        "event":"team-time-trial-men",
        "medal":"B",
        "olympics":"seoul-1988",
        "result":"1:59:47.3",
        "sport":"cycling"
    },
    {
        "athlete":"scott-mcgrory",
        "event":"madison-men",
        "medal":"G",
        "olympics":"sydney-2000",
        "result":"26,0",
        "sport":"cycling"
    },
    {
        "athlete":"scott-mcgrory",
        "event":"team-pursuit-(4000m)-men",
        "medal":"B",
        "olympics":"seoul-1988",
        "result":"4:16.02     (56.245)",
        "sport":"cycling"
    },
    {
        "athlete":"oleksandr-fedenko",
        "event":"team-pursuit-(4000m)-men",
        "medal":"S",
        "olympics":"sydney-2000",
        "result":"",
        "sport":"cycling"
    },
    {
        "athlete":"axel-merckx",
        "event":"individual-road-race-men",
        "medal":"B",
        "olympics":"athens-2004",
        "result":"5h41:52",
        "sport":"cycling"
    },
    {
        "athlete":"stephen-cummings",
        "event":"team-pursuit-(4000m)-men",
        "medal":"S",
        "olympics":"athens-2004",
        "result":"",
        "sport":"cycling"
    },
    {
        "athlete":"karin-thurig",
        "event":"individual-time-trial-women",
        "medal":"B",
        "olympics":"beijing-2008",
        "result":"35:50.99",
        "sport":"cycling"
    },
    {
        "athlete":"karin-thurig",
        "event":"individual-time-trial-women",
        "medal":"B",
        "olympics":"athens-2004",
        "result":"31:54.89",
        "sport":"cycling"
    },
    {
        "athlete":"deirdre-demet-barry",
        "event":"individual-time-trial-women",
        "medal":"S",
        "olympics":"athens-2004",
        "result":"31:35.62",
        "sport":"cycling"
    },
    {
        "athlete":"michael-rich",
        "event":"team-time-trial-men",
        "medal":"G",
        "olympics":"barcelona-1992",
        "result":"2:01:39",
        "sport":"cycling"
    },
    {
        "athlete":"sandra-schumacher",
        "event":"individual-road-race-women",
        "medal":"B",
        "olympics":"los-angeles-1984",
        "result":"",
        "sport":"cycling"
    },
    {
        "athlete":"rebecca-twigg",
        "event":"individual-pursuit-women",
        "medal":"B",
        "olympics":"barcelona-1992",
        "result":"",
        "sport":"cycling"
    },
    {
        "athlete":"rebecca-twigg",
        "event":"individual-road-race-women",
        "medal":"S",
        "olympics":"los-angeles-1984",
        "result":"",
        "sport":"cycling"
    },
    {
        "athlete":"helen-constance-carpenter-phinney",
        "event":"individual-road-race-women",
        "medal":"G",
        "olympics":"los-angeles-1984",
        "result":"2:11:14  (36.210)",
        "sport":"cycling"
    },
    {
        "athlete":"curtis-harnett",
        "event":"sprint-individual-men",
        "medal":"B",
        "olympics":"atlanta-1996",
        "result":"",
        "sport":"cycling"
    },
    {
        "athlete":"curtis-harnett",
        "event":"sprint-individual-men",
        "medal":"B",
        "olympics":"barcelona-1992",
        "result":"",
        "sport":"cycling"
    },
    {
        "athlete":"curtis-harnett",
        "event":"1km-time-trial-men",
        "medal":"S",
        "olympics":"los-angeles-1984",
        "result":"1:06.44    (54.187)",
        "sport":"cycling"
    },
    {
        "athlete":"aleksandr-kirichenko",
        "event":"1km-time-trial-men",
        "medal":"G",
        "olympics":"seoul-1988",
        "result":"1:04.499    (55.814)",
        "sport":"cycling"
    },
    {
        "athlete":"martin-vinnicombe",
        "event":"1km-time-trial-men",
        "medal":"S",
        "olympics":"seoul-1988",
        "result":"1:04.784    (55.569)",
        "sport":"cycling"
    },
    {
        "athlete":"robert-lechner",
        "event":"1km-time-trial-men",
        "medal":"B",
        "olympics":"seoul-1988",
        "result":"1:05.114    (55.287)",
        "sport":"cycling"
    },
    {
        "athlete":"benno-wiss",
        "event":"team-time-trial-men",
        "medal":"S",
        "olympics":"los-angeles-1984",
        "result":"2:02:38",
        "sport":"cycling"
    },
    {
        "athlete":"bernd-grone",
        "event":"individual-road-race-men",
        "medal":"S",
        "olympics":"seoul-1988",
        "result":"4:32:25  (43.345)",
        "sport":"cycling"
    },
    {
        "athlete":"christian-henn",
        "event":"individual-road-race-men",
        "medal":"B",
        "olympics":"seoul-1988",
        "result":"4:32:46  (43.289)",
        "sport":"cycling"
    },
    {
        "athlete":"hennie-kuiper",
        "event":"individual-road-race-men",
        "medal":"G",
        "olympics":"munich-1972",
        "result":"4-14:37",
        "sport":"cycling"
    },
    {
        "athlete":"clyde-sefton",
        "event":"individual-road-race-men",
        "medal":"S",
        "olympics":"munich-1972",
        "result":"at 0:27",
        "sport":"cycling"
    },
    {
        "athlete":"mieczyslaw-nowicki",
        "event":"team-time-trial-men",
        "medal":"S",
        "olympics":"montreal-1976",
        "result":"2:09:13",
        "sport":"cycling"
    },
    {
        "athlete":"mieczyslaw-nowicki",
        "event":"individual-road-race-men",
        "medal":"B",
        "olympics":"montreal-1976",
        "result":"4:47:23",
        "sport":"cycling"
    },
    {
        "athlete":"giuseppe-martinelli",
        "event":"individual-road-race-men",
        "medal":"S",
        "olympics":"montreal-1976",
        "result":"4:47:23",
        "sport":"cycling"
    },
    {
        "athlete":"bernt-johansson",
        "event":"individual-road-race-men",
        "medal":"G",
        "olympics":"montreal-1976",
        "result":"4:46:52  (37.648)",
        "sport":"cycling"
    },
    {
        "athlete":"aleksandr-panfilov",
        "event":"1km-time-trial-men",
        "medal":"S",
        "olympics":"moscow-1980",
        "result":"1:04.845    (55.521 KM/H)",
        "sport":"cycling"
    },
    {
        "athlete":"yave-cahard",
        "event":"sprint-individual-men",
        "medal":"S",
        "olympics":"moscow-1980",
        "result":"",
        "sport":"cycling"
    },
    {
        "athlete":"david-weller",
        "event":"1km-time-trial-men",
        "medal":"B",
        "olympics":"moscow-1980",
        "result":"1:05.241    (55.181 KM/H)",
        "sport":"cycling"
    },
    {
        "athlete":"lothar-thoms",
        "event":"1km-time-trial-men",
        "medal":"G",
        "olympics":"moscow-1980",
        "result":"1:02.955    (57.188 KM/H)",
        "sport":"cycling"
    },
    {
        "athlete":"richard-trinkler",
        "event":"team-time-trial-men",
        "medal":"S",
        "olympics":"los-angeles-1984",
        "result":"2:02:38",
        "sport":"cycling"
    },
    {
        "athlete":"ronald-alexander-kiefel",
        "event":"team-time-trial-men",
        "medal":"B",
        "olympics":"los-angeles-1984",
        "result":"2:02:46",
        "sport":"cycling"
    }
]